beprof/__init__.py
beprof/curve.py
beprof/functions.py
beprof/profile.py
beprof/tests/__init__.py
beprof/tests/test_curve.py
beprof/tests/test_profile.py
beprof-0.1.4.dist-info/AUTHORS.rst
beprof-0.1.4.dist-info/LICENSE
beprof-0.1.4.dist-info/METADATA
beprof-0.1.4.dist-info/WHEEL
beprof-0.1.4.dist-info/top_level.txt
beprof-0.1.4.dist-info/RECORD
