Metadata-Version: 2.1
Name: beprof
Version: 0.1.4
Summary: Beam Profile Analysing Tools
Home-page: https://github.com/DataMedSci/beprof
Author: Leszek Grzanka, Mateusz Krakowski, Agnieszka Rudnicka
Author-email: grzanka@agh.edu.pl
License: GPL
Platform: UNKNOWN
Classifier: Development Status :: 3 - Alpha
Classifier: Intended Audience :: Developers
Classifier: Intended Audience :: Science/Research
Classifier: Topic :: Software Development :: Libraries :: Python Modules
Classifier: Topic :: Scientific/Engineering :: Physics
Classifier: Environment :: Console
Classifier: Operating System :: POSIX :: Linux
Classifier: Operating System :: Unix
Classifier: Operating System :: Microsoft :: Windows
Classifier: Operating System :: MacOS
Classifier: License :: OSI Approved :: MIT License
Classifier: Programming Language :: Python :: 2.7
Classifier: Programming Language :: Python :: 3.2
Classifier: Programming Language :: Python :: 3.3
Classifier: Programming Language :: Python :: 3.4
Classifier: Programming Language :: Python :: 3.5
Classifier: Programming Language :: Python :: 3.6
Requires-Dist: numpy (>=1.8); python_version < "3.0" or python_version >= "3.4"
Requires-Dist: numpy (<1.12,>=1.8); python_version >= "3.2" and python_version < "3.4"
